ponytool/__init__.py
ponytool/cli.py
ponytool/deps/__init__.py
ponytool/deps/analyzer.py
ponytool/deps/collect_imports.py
ponytool/deps/collect_packages.py
ponytool/deps/generate.py
ponytool/deps/scanner.py
ponytool/deps/writer.py
ponytool/deps/scan/__init__.py
ponytool/deps/scan/collector.py
ponytool/deps/scan/env.py
ponytool/deps/scan/metadata.py
ponytool/deps/scan/site_packages.py
ponytool/project/__init__.py
ponytool/project/content_cfg.py
ponytool/project/content_from_file.py
ponytool/project/content_helper.py
ponytool/project/bootstrap/__init__.py
ponytool/project/bootstrap/bootstrap.py
ponytool/project/bootstrap/template/__init__.py
ponytool/project/bootstrap/template/bootstrap_cfg.py
ponytool/pytest_scripts/__init__.py
ponytool/pytest_scripts/run_test.py
ponytool/utils/__init__.py
ponytool/utils/shell.py
ponytool/utils/ui.py
ponytool-2.0.4.dist-info/licenses/LICENSE
ponytool-2.0.4.dist-info/METADATA
ponytool-2.0.4.dist-info/WHEEL
ponytool-2.0.4.dist-info/entry_points.txt
ponytool-2.0.4.dist-info/top_level.txt
ponytool-2.0.4.dist-info/RECORD
