Metadata-Version: 2.4
Name: ponytool
Version: 2.0.4
Summary: CLI toolbox to reduce everyday Python project setup routine
License: MIT
Project-URL: Homepage, https://github.com/PonyPaPony/PonyTool
Project-URL: Repository, https://github.com/PonyPaPony/PonyTool
Project-URL: Issues, https://github.com/PonyPaPony/PonyTool/issues
Requires-Python: >=3.10
License-File: LICENSE
Requires-Dist: rich<15.0,>=13.0
Dynamic: license-file
